CHANGES.rst
README.rst
setup.py
fjd/__init__.py
fjd/core_process.py
fjd/dispatcher.py
fjd/main.py
fjd/recruiter.py
fjd/sshtools.py
fjd/utils.py
fjd/worker.py
fjd.egg-info/PKG-INFO
fjd.egg-info/SOURCES.txt
fjd.egg-info/dependency_links.txt
fjd.egg-info/requires.txt
fjd.egg-info/top_level.txt
fjd/scripts/bgscreen
fjd/scripts/fjd
fjd/scripts/fjd-dispatcher
fjd/scripts/fjd-recruiter
fjd/scripts/fjd-worker