Metadata-Version: 1.1
Name: fjd
Version: 0.1.55
Summary: Job distribution for everyone
Home-page: http://github.com/nhoening/fjd/
Author: Nicolas Höning
Author-email: iam@nicolashoening.de
License: Apache Software License
Platform: Unix
Classifier: Programming Language :: Python :: 2.7
Classifier: Development Status :: 4 - Beta
Classifier: Natural Language :: English
Classifier: Environment :: Console
Classifier: Intended Audience :: Developers
Classifier: License :: OSI Approved :: Apache Software License
Classifier: Operating System :: POSIX
Classifier: Topic :: Software Development :: Libraries :: Python Modules
Classifier: Topic :: System :: Distributed Computing
Classifier: Topic :: Utilities
